Workbook

Sheet Instrucciones
B1: Plantilla de datos reales — ERP Vehículos Eléctricos
B3: Llena las hojas en el orden de abajo. Cada hoja corresponde a una pantalla del sistema.
B4: No escribas contraseñas en este archivo: los usuarios reciben su contraseña por un medio privado.
B6: Leyenda
C7: Amarillo: celda para llenar
C8: Gris: fila de EJEMPLO (no se carga; puedes borrarla)
C9: Verde: se calcula sola, no la edites
A11: # | B11: Hoja | C11: Qué contiene | D11: Cómo se carga en el sistema
A12: 1 | B12: Preguntas negocio | C12: Decisiones del cliente que cambian costos y precios. RESPONDER PRIMERO. | D12: Se ajusta en la configuración del sistema
A13: 2 | B13: Ubicaciones | C13: Almacenes, showrooms y talleres (3 ya existen) | D13: Admin → Ubicaciones
A14: 3 | B14: Usuarios | C14: Personal que usará el sistema y su rol | D14: Supabase → Add user, luego Admin → Usuarios
A15: 4 | B15: Modelos | C15: Ficha técnica y precio EXW de cada modelo XSDU | D15: Admin → Modelos
A16: 5 | B16: Lote | C16: Datos y costos del contenedor (embarque, DAM, fletes, impuestos) | D16: Lotes → Nuevo lote → pestañas Datos y Costos
A17: 6 | B17: Packing list | C17: Cuántas unidades de cada modelo trae el lote | D17: Lotes → pestaña Packing list
A18: 7 | B18: Unidades | C18: VIN, motor y colores de cada unidad física | D18: Inventario → Registro de unidades (pegar desde Excel)
A19: 8 | B19: Baterías (opcional) | C19: Seriales de baterías si el proveedor los entrega | D19: Taller → cada unidad (el técnico las escanea)

Sheet Preguntas negocio
A1: # | B1: Pregunta | C1: Valor que usa hoy el sistema | D1: Respuesta del cliente | E1: Por qué importa
A2: 1 | B2: ¿IGV, IPM y percepción de importación son crédito fiscal (empresa en Régimen General)? | C2: Se cargan al costo (SÍ cuentan como costo) | E2: Si son crédito fiscal, el costo y todos los precios bajan ~18% del CIF. LA MÁS IMPORTANTE.
A3: 2 | B3: ¿Los precios de venta incluyen IGV? | C3: Sí, incluyen IGV | E3: Define cómo se muestra el precio al cliente final
A4: 3 | B4: Margen x1 (venta por unidad) | C4: 20% (x3 y x6 desactivados por ahora) | E4: Precio = Costo / (1 − Margen)
A5: 4 | B5: ¿El 20% es sobre el PRECIO de venta o ENCIMA del costo? | C5: Sobre el precio: costo S/ 1,000 → precio S/ 1,250 | E5: Si es encima del costo (S/ 1,000 → S/ 1,200), en el sistema se pone 16.67%
A6: 5 | B6: Meses de garantía general (¿igual para todos los modelos?) | C6: 12 meses | E6: Se genera automáticamente al vender
A7: 6 | B7: Meses de garantía de baterías | C7: 6 meses | E7: Se genera automáticamente al vender
A8: 7 | B8: ¿Las ventas x3 y x6 pueden mezclar modelos distintos? | C8: Sí, se pueden mezclar | E8: Regla para aplicar precio mayorista/distribuidor
A9: 8 | B9: ¿El vendedor puede dar descuentos? | C9: No, solo el admin cambia precios | E9: Si sí, se agrega un límite de descuento
A10: 9 | B10: ¿Hay unidades que ya existían antes del sistema (armadas en tienda o ya vendidas)? | C10: — | E10: Define si se cargan como inventario inicial (ver hoja Unidades, columna Situación)
A11: 10 | B11: Costo de armado por unidad | C11: S/ 60.00 | E11: Se suma al costo de cada unidad

Sheet Ubicaciones
A1: Nombre | B1: Tipo | C1: Dirección | D1: Notas
A2: Almacén Central | B2: almacen | D2: Ya existe en el sistema (corrige el nombre si hace falta)
A3: Showroom Piérola | B3: showroom | D3: Ya existe en el sistema (corrige el nombre si hace falta)
A4: Taller de Ensamble | B4: taller | D4: Ya existe en el sistema (corrige el nombre si hace falta)

Sheet Usuarios
A1: Nombre completo | B1: Email | C1: Rol | D1: Notas | E1: Roles: admin = todo (ve costos) · tecnico = registro de unidades, baterías e inspección (no ve costos ni precios) · vendedor = stock, precios y ventas (no ve costos).
A2: EJEMPLO: Ana Pérez | B2: ana.perez@empresa.pe | C2: vendedor | D2: Fila de ejemplo — no se carga

Sheet Modelos
A1: Código modelo | B1: Nombre comercial | C1: Categoría | D1: Voltaje (V) | E1: Baterías 12V | F1: Amperaje batería (Ah) | G1: Potencia motor (W) | H1: Volumen embalado (CBM, m³) | I1: Precio EXW unitario (US$) | J1: Garantía general (meses) | K1: Garantía baterías (meses)
A2: EJEMPLO-01 | B2: Moto urbana 1000W | C2: bicimoto | D2: 60 | E2: =IF(D2="","",D2/12) -> 5 | F2: 20 | G2: 1000 | H2: 0.45 | I2: 420 | J2: 12 | K2: 6
A3: XSDU-17 | E3: =IF(D3="","",D3/12)
A4: XSDU-23 | E4: =IF(D4="","",D4/12)
A5: XSDU-24 | E5: =IF(D5="","",D5/12)
A6: XSDU-25 | E6: =IF(D6="","",D6/12)
A7: XSDU-29 | E7: =IF(D7="","",D7/12)
A8: XSDU-31 | E8: =IF(D8="","",D8/12)
A9: XSDU-35 | E9: =IF(D9="","",D9/12)
A10: XSDU-36 | E10: =IF(D10="","",D10/12)
E11: =IF(D11="","",D11/12)
E12: =IF(D12="","",D12/12)
E13: =IF(D13="","",D13/12)
E14: =IF(D14="","",D14/12)
E15: =IF(D15="","",D15/12)
E16: =IF(D16="","",D16/12)
E17: =IF(D17="","",D17/12)
E18: =IF(D18="","",D18/12)
E19: =IF(D19="","",D19/12)
E20: =IF(D20="","",D20/12)
E21: =IF(D21="","",D21/12)
E22: =IF(D22="","",D22/12)
... E30: =IF(D30="","",D30/12)

Sheet Lote
A1: Campo | B1: Valor | C1: Unidad | D1: De dónde sale / notas | F1: Si tienes más de un contenedor, duplica esta hoja (Lote 2, Lote 3…).
A2: Código de embarque | B2: 117GZH2606089 | D2: Del documento original — confirmar
A3: Nro. DAM | B3: 118-2026-10-361056-01-0-00 | D3: Del documento original — confirmar
A4: Proveedor | D4: Razón social del proveedor
A5: Fecha de embarque | D5: dd/mm/aaaa
A6: Fecha de llegada | D6: dd/mm/aaaa
A7: Tipo de cambio | B7: 3.78 | C7: S/ por US$ | D7: El usado en la DAM — confirmar
A8: FOB total | C8: US$ | D8: Factura comercial
A9: Flete internacional | C9: US$ | D9: Se reparte por volumen (CBM)
A10: Gastos del agente de carga | C10: US$ | D10: Se reparte por volumen (CBM)
A11: Ad Valorem | C11: S/ | D11: Liquidación de la DAM
A12: IGV de importación | C12: S/ | D12: Liquidación de la DAM
A13: IPM | C13: S/ | D13: Liquidación de la DAM
A14: Percepción | C14: S/ | D14: Liquidación de la DAM
A15: Flete nacional (Callao → destino) | C15: S/ | D15: Se reparte por volumen (CBM)
A16: Alquiler del periodo | C16: S/ | D16: Se reparte por cantidad de unidades
A17: Sueldos del periodo | C17: S/ | D17: Se reparte por cantidad de unidades
A18: Publicidad inicial | C18: S/ | D18: Se reparte por cantidad de unidades
A19: Costo de armado por unidad | B19: 60 | C19: S/ | D19: Valor por defecto del sistema
A21: Total impuestos SUNAT | B21: =SUM(B11:B14) -> 0 | C21: S/
A22: Total EXW del packing list | B22: =SUM('Packing list'!G2:G40) -> 0 | C22: US$ | D22: Referencia: debería ser cercano al FOB total
A23: Total unidades del packing list | B23: =SUM('Packing list'!B2:B40) -> 0 | C23: unid.

Sheet Packing list
A1: Código modelo | B1: Cantidad (packing list) | C1: Cantidad (DAM) | D1: EXW unitario factura (US$) — solo si difiere del catálogo | E1: EXW unitario usado (US$) | F1: CBM unitario usado | G1: EXW total (US$) | H1: CBM total | J1: Si la cantidad del packing list y la de la DAM difieren, el sistema lo marca en Auditoría.
E2: =IF(A2="","",IF(D2<>"",D2,IFERROR(INDEX(Modelos!$I$3:$I$30,MATCH(A2,Modelos!$A$3:$A$30,0)),"¿modelo?"))) | F2: =IF(A2="","",IFERROR(INDEX(Modelos!$H$3:$H$30,MATCH(A2,Modelos!$A$3:$A$30,0)),"¿modelo?")) | G2: =IF(OR(A2="",B2=""),"",IFERROR(B2*E2,"")) | H2: =IF(OR(A2="",B2=""),"",IFERROR(B2*F2,""))
E3: =IF(A3="","",IF(D3<>"",D3,IFERROR(INDEX(Modelos!$I$3:$I$30,MATCH(A3,Modelos!$A$3:$A$30,0)),"¿modelo?"))) | F3: =IF(A3="","",IFERROR(INDEX(Modelos!$H$3:$H$30,MATCH(A3,Modelos!$A$3:$A$30,0)),"¿modelo?")) | G3: =IF(OR(A3="",B3=""),"",IFERROR(B3*E3,"")) | H3: =IF(OR(A3="",B3=""),"",IFERROR(B3*F3,""))
E4: =IF(A4="","",IF(D4<>"",D4,IFERROR(INDEX(Modelos!$I$3:$I$30,MATCH(A4,Modelos!$A$3:$A$30,0)),"¿modelo?"))) | F4: =IF(A4="","",IFERROR(INDEX(Modelos!$H$3:$H$30,MATCH(A4,Modelos!$A$3:$A$30,0)),"¿modelo?")) | G4: =IF(OR(A4="",B4=""),"",IFERROR(B4*E4,"")) | H4: =IF(OR(A4="",B4=""),"",IFERROR(B4*F4,""))
E5: =IF(A5="","",IF(D5<>"",D5,IFERROR(INDEX(Modelos!$I$3:$I$30,MATCH(A5,Modelos!$A$3:$A$30,0)),"¿modelo?"))) | F5: =IF(A5="","",IFERROR(INDEX(Modelos!$H$3:$H$30,MATCH(A5,Modelos!$A$3:$A$30,0)),"¿modelo?")) | G5: =IF(OR(A5="",B5=""),"",IFERROR(B5*E5,"")) | H5: =IF(OR(A5="",B5=""),"",IFERROR(B5*F5,""))
E6: =IF(A6="","",IF(D6<>"",D6,IFERROR(INDEX(Modelos!$I$3:$I$30,MATCH(A6,Modelos!$A$3:$A$30,0)),"¿modelo?"))) | F6: =IF(A6="","",IFERROR(INDEX(Modelos!$H$3:$H$30,MATCH(A6,Modelos!$A$3:$A$30,0)),"¿modelo?")) | G6: =IF(OR(A6="",B6=""),"",IFERROR(B6*E6,"")) | H6: =IF(OR(A6="",B6=""),"",IFERROR(B6*F6,""))
E7: =IF(A7="","",IF(D7<>"",D7,IFERROR(INDEX(Modelos!$I$3:$I$30,MATCH(A7,Modelos!$A$3:$A$30,0)),"¿modelo?"))) | F7: =IF(A7="","",IFERROR(INDEX(Modelos!$H$3:$H$30,MATCH(A7,Modelos!$A$3:$A$30,0)),"¿modelo?")) | G7: =IF(OR(A7="",B7=""),"",IFERROR(B7*E7,"")) | H7: =IF(OR(A7="",B7=""),"",IFERROR(B7*F7,""))
E8: =IF(A8="","",IF(D8<>"",D8,IFERROR(INDEX(Modelos!$I$3:$I$30,MATCH(A8,Modelos!$A$3:$A$30,0)),"¿modelo?"))) | F8: =IF(A8="","",IFERROR(INDEX(Modelos!$H$3:$H$30,MATCH(A8,Modelos!$A$3:$A$30,0)),"¿modelo?")) | G8: =IF(OR(A8="",B8=""),"",IFERROR(B8*E8,"")) | H8: =IF(OR(A8="",B8=""),"",IFERROR(B8*F8,""))
E9: =IF(A9="","",IF(D9<>"",D9,IFERROR(INDEX(Modelos!$I$3:$I$30,MATCH(A9,Modelos!$A$3:$A$30,0)),"¿modelo?"))) | F9: =IF(A9="","",IFERROR(INDEX(Modelos!$H$3:$H$30,MATCH(A9,Modelos!$A$3:$A$30,0)),"¿modelo?")) | G9: =IF(OR(A9="",B9=""),"",IFERROR(B9*E9,"")) | H9: =IF(OR(A9="",B9=""),"",IFERROR(B9*F9,""))
E10: =IF(A10="","",IF(D10<>"",D10,IFERROR(INDEX(Modelos!$I$3:$I$30,MATCH(A10,Modelos!$A$3:$A$30,0)),"¿modelo?"))) | F10: =IF(A10="","",IFERROR(INDEX(Modelos!$H$3:$H$30,MATCH(A10,Modelos!$A$3:$A$30,0)),"¿modelo?")) | G10: =IF(OR(A10="",B10=""),"",IFERROR(B10*E10,"")) | H10: =IF(OR(A10="",B10=""),"",IFERROR(B10*F10,""))
E11: =IF(A11="","",IF(D11<>"",D11,IFERROR(INDEX(Modelos!$I$3:$I$30,MATCH(A11,Modelos!$A$3:$A$30,0)),"¿modelo?"))) | F11: =IF(A11="","",IFERROR(INDEX(Modelos!$H$3:$H$30,MATCH(A11,Modelos!$A$3:$A$30,0)),"¿modelo?")) | G11: =IF(OR(A11="",B11=""),"",IFERROR(B11*E11,"")) | H11: =IF(OR(A11="",B11=""),"",IFERROR(B11*F11,""))
E12: =IF(A12="","",IF(D12<>"",D12,IFERROR(INDEX(Modelos!$I$3:$I$30,MATCH(A12,Modelos!$A$3:$A$30,0)),"¿modelo?"))) | F12: =IF(A12="","",IFERROR(INDEX(Modelos!$H$3:$H$30,MATCH(A12,Modelos!$A$3:$A$30,0)),"¿modelo?")) | G12: =IF(OR(A12="",B12=""),"",IFERROR(B12*E12,"")) | H12: =IF(OR(A12="",B12=""),"",IFERROR(B12*F12,""))
E13: =IF(A13="","",IF(D13<>"",D13,IFERROR(INDEX(Modelos!$I$3:$I$30,MATCH(A13,Modelos!$A$3:$A$30,0)),"¿modelo?"))) | F13: =IF(A13="","",IFERROR(INDEX(Modelos!$H$3:$H$30,MATCH(A13,Modelos!$A$3:$A$30,0)),"¿modelo?")) | G13: =IF(OR(A13="",B13=""),"",IFERROR(B13*E13,"")) | H13: =IF(OR(A13="",B13=""),"",IFERROR(B13*F13,""))
... E40: =IF(A40="","",IF(D40<>"",D40,IFERROR(INDEX(Modelos!$I$3:$I$30,MATCH(A40,Modelos!$A$3:$A$30,0)),"¿modelo?"))) | F40: =IF(A40="","",IFERROR(INDEX(Modelos!$H$3:$H$30,MATCH(A40,Modelos!$A$3:$A$30,0)),"¿modelo?")) | G40: =IF(OR(A40="",B40=""),"",IFERROR(B40*E40,"")) | H40: =IF(OR(A40="",B40=""),"",IFERROR(B40*F40,""))
A42: TOTAL | B42: =SUM(B2:B40) -> 0 | C42: =SUM(C2:C40) -> 0 | G42: =SUM(G2:G40) -> 0 | H42: =SUM(H2:H40) -> 0

Sheet Unidades
A1: VIN / chasis | B1: Nro. de motor | C1: Código modelo | D1: Color primario | E1: Color secundario | F1: Situación actual | G1: Notas | I1: Una fila por unidad física. Los VIN y números de motor no pueden repetirse. Las primeras 5 columnas se pegan tal cual en Inventario → Registro de unidades.
A2: LZSJCMLC5R1000001 | B2: QS1000W2406001 | C2: XSDU-29 | D2: Rojo | E2: Negro | F2: en_caja | G2: Fila de ejemplo — no se carga

Sheet Baterías (opcional)
A1: VIN / chasis | B1: Serial batería 1 | C1: Serial batería 2 | D1: Serial batería 3 | E1: Serial batería 4 | F1: Serial batería 5 (60V/72V) | G1: Serial batería 6 (solo 72V) | I1: Solo si el proveedor entrega los seriales. Si no, el técnico los escanea en el Taller al armar cada unidad.
A2: LZSJCMLC5R1000001 | B2: BT20A-0001 | C2: BT20A-0002 | D2: BT20A-0003 | E2: BT20A-0004 | F2: BT20A-0005
